StatsChitran/__init__.py
StatsChitran/module1.py
StatsChitran/module_gauss.py
StatsChitran/module_lineval.py
StatsChitran/module_lorentz.py
StatsChitran/module_seqn.py
StatsChitran/module_vec.py
statschitran-0.3.9.dist-info/METADATA
statschitran-0.3.9.dist-info/WHEEL
statschitran-0.3.9.dist-info/top_level.txt
statschitran-0.3.9.dist-info/RECORD
