Metadata-Version: 2.4
Name: StatsChitran
Version: 0.3.9
Summary: A collection of few statistical functions in a package for direct use
Home-page: https://github.com/Chitran1987/StatsChitranPython
Author: Chitran Ghosal
Author-email: ghosal.chitran@gmail.com
Classifier: Programming Language :: Python :: 3
Classifier: License :: OSI Approved :: MIT License
Classifier: Operating System :: OS Independent
Requires-Dist: numpy
Requires-Dist: pandas
Requires-Dist: matplotlib
Dynamic: author
Dynamic: author-email
Dynamic: classifier
Dynamic: home-page
Dynamic: requires-dist
Dynamic: summary
